sphinxjp/__init__.py
sphinxjp/usaturn.py
sphinxjp.usaturn-0.2.0.dist-info/DESCRIPTION.rst
sphinxjp.usaturn-0.2.0.dist-info/METADATA
sphinxjp.usaturn-0.2.0.dist-info/metadata.json
sphinxjp.usaturn-0.2.0.dist-info/RECORD
sphinxjp.usaturn-0.2.0.dist-info/top_level.txt
sphinxjp.usaturn-0.2.0.dist-info/WHEEL
