Metadata-Version: 2.0
Name: sphinxjp.usaturn
Version: 0.2.0
Summary: a sphinx extension to add new admonition named `usaturn`
Home-page: http://bitbucket.com/tk0miya/sphinxjp.usaturn
Author: Takeshi Komiya
Author-email: i.tkomiya at gmail.com
License: Apache License 2.0
Download-URL: http://pypi.python.org/pypi/sphinxjp.usaturn
Keywords: document
Platform: UNKNOWN
Classifier: Development Status :: 4 - Beta
Classifier: Environment :: Console
Classifier: Intended Audience :: System Administrators
Classifier: License :: OSI Approved :: Apache Software License
Classifier: Programming Language :: Python
Classifier: Programming Language :: Python :: 2.7
Classifier: Programming Language :: Python :: 3.4
Classifier: Topic :: Software Development
Classifier: Topic :: Software Development :: Documentation
Classifier: Topic :: Text Processing :: Markup
